ZtModTcp/ZtModTcp.py
ZtModTcp/ZtRobot_MC.py
ZtModTcp/ZtRobot_R4.py
ZtModTcp/ZtRobot_S4.py
ZtModTcp/__init__.py
ZtModTcp-1.1.1.dist-info/LICENSE
ZtModTcp-1.1.1.dist-info/METADATA
ZtModTcp-1.1.1.dist-info/WHEEL
ZtModTcp-1.1.1.dist-info/top_level.txt
ZtModTcp-1.1.1.dist-info/RECORD
