Metadata-Version: 2.1
Name: ZtModTcp
Version: 1.1.1
Summary: A VSR virtual library controller package
Home-page: https://github.com/pypa/sampleproject
Author: ZbChenEF
Author-email: 531047408@qq.com
License: UNKNOWN
Platform: UNKNOWN
Classifier: Programming Language :: Python :: 3
Classifier: License :: OSI Approved :: MIT License
Classifier: Operating System :: OS Independent
Requires-Python: >=3.6
Requires-Dist: modbus-tk (>=1.1.2)
Requires-Dist: setuptools (>=56.0.0)
